django_fullname_localization/__init__.py
django_fullname_localization/admin.py
django_fullname_localization/apps.py
django_fullname_localization/models.py
django_fullname_localization/tests.py
django_fullname_localization/views.py
django_fullname_localization/migrations/__init__.py
django_fullname_localization-0.2.2.dist-info/licenses/LICENSE
django_fullname_localization-0.2.2.dist-info/METADATA
django_fullname_localization-0.2.2.dist-info/WHEEL
django_fullname_localization-0.2.2.dist-info/top_level.txt
django_fullname_localization-0.2.2.dist-info/RECORD
